{"id":"B4602BD3-7CD6-43C0-8BBF-68EBAE947DE3","validationEntity":{"analysedDataType":"auto","dataResult":{"createdDate":"2022-06-29T02:30:04Z"}},"modelEntity":{"createdDate":"2022-06-29T02:30:04Z","id":"5F4CE4A7-E56C-4849-95B0-A9AD189DC8D5","experimentID":"52BC91F8-A145-42EC-B0BA-3FBCB4A2247F","title":"","modifiedDate":"2022-06-29T02:30:04Z","preferredFilename":"","version":"1.0","modelURL":"Snapshots\/WorkoutClassifier%203%20Iteration%2080.mlmodel"},"version":"1.0","settingEntity":{"augmentations":[],"harIsCustomActionDuration":false,"seedType":"default","harActionDuration":2,"transferLearningEmbeddingType":"dynamic","harTargetFrameRate":30,"featureNames":[],"algorithmType":"maxEnt","harVideoAugmentations":1,"taskType":"actionClassifier","handPoseClassifierAugmentations":[],"handActionClassifierAugmentations":[],"styleTransferAlgorithmType":"image","iterationCount":80},"state":"trained","trainingEntity":{"finishTime":"2022-06-29T02:29:32Z","recipeTrainingResults":{"humanActionRecognizer":{"confusionMatrix":[{"expected":"None","actual":"None","count":5539},{"expected":"None","actual":"Squat","count":942},{"expected":"Squat","actual":"Squat","count":4246}],"statsByLabel":{"None":{"count":5539,"precisionRecall":{"success":{"recall":1,"precision":0.85465205986730441}}},"Squat":{"count":5188,"precisionRecall":{"success":{"recall":0.81842713955281421,"precision":1}}}},"accuracy":0.91218420807308664}},"dataResult":{"itemsCount":160,"createdDate":"2022-06-29T02:30:04Z","dataURL":"file:\/\/\/Users\/katiejackson\/Desktop\/ashayotovich\/Joule-Power-Training\/trainingData3\/","dataSourceID":"6CAB4F0B-4E92-427B-8C79-34BA23195743","classesCount":2,"analysis":{"summary":{"canUseValidation":1,"classCount":2,"sampleCount":160},"issues":[{"description":"2 classes found, including None, Squat.","severity":"debug"},{"description":"160 action video clips found, automatically creating validation set.","severity":"good"},{"description":"Smallest class is \"Squat\" with 80 action video clips.","severity":"debug"},{"description":"Largest class is \"None\" with 80 action video clips.","severity":"debug"}],"classifierAnalysis":{"labelStats":{"None":80,"Squat":80}}}},"dataURL":"file:\/\/\/Users\/katiejackson\/Desktop\/ashayotovich\/Joule-Power-Training\/trainingData3\/","featureExtractionCheckpointMayBeAvailable":false,"recipeValidationResults":{"humanActionRecognizer":{"confusionMatrix":[{"expected":"None","actual":"None","count":521},{"expected":"None","actual":"Squat","count":60},{"expected":"Squat","actual":"Squat","count":462}],"statsByLabel":{"None":{"count":521,"precisionRecall":{"success":{"recall":1,"precision":0.89672977624784855}}},"Squat":{"count":522,"precisionRecall":{"success":{"recall":0.88505747126436785,"precision":1}}}},"accuracy":0.94247363374880155}},"progress":[{"isLast":false,"percentComplete":0,"currentRowIndex":0,"count":1,"tableDone":false,"harColumnHeader":{"hasValidation":true,"loss":0.0064343167468905423,"trainingAccuracy":0.66766107082366943,"iterationCount":1,"validationAccuracy":0.59156280755996704,"elapsedTime":191.19762599468231},"tableIndex":1},{"isLast":false,"percentComplete":0,"currentRowIndex":0,"count":10,"tableDone":false,"harColumnHeader":{"hasValidation":true,"loss":0.0064343167468905423,"trainingAccuracy":0.66766107082366943,"iterationCount":10,"validationAccuracy":0.59156280755996704,"elapsedTime":0},"tableIndex":1},{"isLast":false,"percentComplete":0,"currentRowIndex":0,"count":20,"tableDone":false,"harColumnHeader":{"hasValidation":true,"loss":0.0011401368537917733,"trainingAccuracy":0.8766663670539856,"iterationCount":20,"validationAccuracy":0.83892619609832764,"elapsedTime":0},"tableIndex":1},{"isLast":false,"percentComplete":0,"currentRowIndex":0,"count":30,"tableDone":false,"harColumnHeader":{"hasValidation":true,"loss":0.0074795987457036972,"trainingAccuracy":0.71063673496246338,"iterationCount":30,"validationAccuracy":0.65100669860839844,"elapsedTime":0},"tableIndex":1},{"isLast":false,"percentComplete":0,"currentRowIndex":0,"count":40,"tableDone":false,"harColumnHeader":{"hasValidation":true,"loss":0.0032377797178924084,"trainingAccuracy":0.92868465185165405,"iterationCount":40,"validationAccuracy":0.9424736499786377,"elapsedTime":0},"tableIndex":1},{"isLast":false,"percentComplete":0,"currentRowIndex":0,"count":50,"tableDone":false,"harColumnHeader":{"hasValidation":true,"loss":0.0024596927687525749,"trainingAccuracy":0.84096205234527588,"iterationCount":50,"validationAccuracy":0.89645254611968994,"elapsedTime":0},"tableIndex":1},{"isLast":false,"percentComplete":0,"currentRowIndex":0,"count":60,"tableDone":false,"harColumnHeader":{"hasValidation":true,"loss":0.0014528000028803945,"trainingAccuracy":0.94192224740982056,"iterationCount":60,"validationAccuracy":0.93096834421157837,"elapsedTime":0},"tableIndex":1},{"isLast":false,"percentComplete":0,"currentRowIndex":0,"count":70,"tableDone":false,"harColumnHeader":{"hasValidation":true,"loss":0.0013295745011419058,"trainingAccuracy":0.52064883708953857,"iterationCount":70,"validationAccuracy":0.49952059984207153,"elapsedTime":0},"tableIndex":1},{"isLast":false,"percentComplete":0,"currentRowIndex":0,"count":80,"tableDone":false,"harColumnHeader":{"hasValidation":true,"loss":0.00043106696102768199,"trainingAccuracy":0.91218417882919312,"iterationCount":80,"validationAccuracy":0.9424736499786377,"elapsedTime":0},"tableIndex":1}],"trainingAccuracy":0.91218420807308664,"checkpointMetrics":{"60":{"metrics":{"Validation Accuracy":0.93096834421157837,"Train Loss":0.0014528000028803945,"Train Accuracy":0.94192224740982056},"createdDate":"2022-06-29T02:28:44Z","iteration":60},"50":{"metrics":{"Validation Accuracy":0.89645254611968994,"Train Loss":0.0024596927687525749,"Train Accuracy":0.84096205234527588},"createdDate":"2022-06-29T02:28:21Z","iteration":50},"40":{"metrics":{"Validation Accuracy":0.9424736499786377,"Train Loss":0.0032377797178924084,"Train Accuracy":0.92868465185165405},"createdDate":"2022-06-29T02:27:57Z","iteration":40},"30":{"metrics":{"Validation Accuracy":0.65100669860839844,"Train Loss":0.0074795987457036972,"Train Accuracy":0.71063673496246338},"createdDate":"2022-06-29T02:27:34Z","iteration":30},"20":{"metrics":{"Validation Accuracy":0.83892619609832764,"Train Loss":0.0011401368537917733,"Train Accuracy":0.8766663670539856},"createdDate":"2022-06-29T02:27:09Z","iteration":20},"80":{"metrics":{"Validation Accuracy":0.9424736499786377,"Train Loss":0.00043106696102768199,"Train Accuracy":0.91218417882919312},"createdDate":"2022-06-29T02:29:31Z","iteration":80},"10":{"metrics":{"Validation Accuracy":0.59156280755996704,"Train Loss":0.0064343167468905423,"Train Accuracy":0.66766107082366943},"createdDate":"2022-06-29T02:26:43Z","iteration":10},"70":{"metrics":{"Validation Accuracy":0.49952059984207153,"Train Loss":0.0013295745011419058,"Train Accuracy":0.52064883708953857},"createdDate":"2022-06-29T02:29:08Z","iteration":70}},"analysedDataType":"none","dataSourceID":"6CAB4F0B-4E92-427B-8C79-34BA23195743","snapshottableCheckpoints":{"80":{"modelURL":"file:\/\/\/var\/folders\/q4\/x7clfd5x3qv56rdlv4xckwjc0000gn\/T\/checkpoint.sessions\/52BC91F8-A145-42EC-B0BA-3FBCB4A2247F\/training-000000080.checkpoint.model\/checkpointModel.mlmodel","createdDate":"2022-06-29T02:29:31Z","iteration":80}},"resumableCheckpoint":{"checkpointURL":"file:\/\/\/var\/folders\/q4\/x7clfd5x3qv56rdlv4xckwjc0000gn\/T\/checkpoint.sessions\/52BC91F8-A145-42EC-B0BA-3FBCB4A2247F\/training-000000080.checkpoint","createdDate":"2022-06-29T02:29:31Z","iteration":80},"validationAccuracy":0.94247363374880155,"startTime":"2022-06-29T02:23:32Z"},"createdDate":"2022-06-29T02:30:04Z","evaluationContainerEntity":{"testingEvaluationEntity":{"id":"26d07d1b-e346-45a3-9030-2b75eae3f51e","createdDate":"2022-06-29T02:30:04Z","dataResult":{"createdDate":"2022-06-29T02:30:04Z"},"analysedDataType":"none"},"createdDate":"2022-06-29T02:30:04Z","id":"17a01dab-d918-48f1-a059-e696ee7de3e2","trainingEvaluationEntity":{"id":"2d9cdc26-6529-4f0b-8648-19981f390c1c","createdDate":"2022-06-29T02:30:04Z","dataURL":"file:\/\/\/Users\/katiejackson\/Desktop\/ashayotovich\/Joule-Power-Training\/trainingData3\/","dataSourceID":"6CAB4F0B-4E92-427B-8C79-34BA23195743","dataResult":{"dataURL":"file:\/\/\/Users\/katiejackson\/Desktop\/ashayotovich\/Joule-Power-Training\/trainingData3\/","createdDate":"2022-06-29T02:30:04Z","dataSourceID":"6CAB4F0B-4E92-427B-8C79-34BA23195743"},"analysedDataType":"none"},"previewType":"actionClassifier","modifiedDate":"2022-06-29T02:30:04Z","validationEvaluationEntity":{"id":"acc51f55-ca50-4ab8-ba99-c12bf1c9dc0b","createdDate":"2022-06-29T02:30:04Z","dataResult":{"createdDate":"2022-06-29T02:30:04Z"},"analysedDataType":"auto"},"evaluationEntities":[]},"evaluationEntities":[],"activityEntities":["experimentCreated",[{"id":"1AA26331-99DE-4DEE-A28C-1DAE4DBC1EF1","title":"Model Source Created","createdDate":"2022-06-29T02:21:49Z","event":"experimentCreated","subtitle":"WorkoutClassifier 3"}],"trainingStarted",[{"id":"5FE58095-6964-45D9-A021-2D5497E96013","title":"Training Started","createdDate":"2022-06-29T02:23:32Z","event":"trainingStarted","subtitle":"80 iterations"}],"trainingFinished",[{"id":"E21AEADF-3E94-414A-9D41-8782DB9124A5","title":"Training Completed","createdDate":"2022-06-29T02:29:32Z","event":"trainingFinished","subtitle":"80 iterations"}],"trainingDataAdded",[{"id":"05DA2401-0DAC-4FEB-9BCB-CDF634EE2086","title":"Training Data Added","createdDate":"2022-06-29T02:21:55Z","event":"trainingDataAdded","subtitle":"trainingData3"}]],"title":"Iteration 80","evaluationEntity":{"id":"653a8b4c-0cb8-4f81-acc5-b9e6e7f7ecc1","createdDate":"2022-06-29T02:30:04Z","dataResult":{},"analysedDataType":"none"},"evaluationState":"uninitialized","snapshotRole":{"snapshotIteration":80,"snapshotParent":"52BC91F8-A145-42EC-B0BA-3FBCB4A2247F"},"modifiedDate":"2022-06-29T02:30:04Z","contentDataResult":{"createdDate":"2022-06-29T02:21:49Z"},"preferredFilename":"WorkoutClassifier 3 Iteration 80"}